README.md
setup.py
emopt/__init__.py
emopt/adjoint_method.py
emopt/fdfd.py
emopt/fomutils.py
emopt/grid.py
emopt/misc.py
emopt/modedata.py
emopt/modes.py
emopt/optimizer.py
emopt.egg-info/PKG-INFO
emopt.egg-info/SOURCES.txt
emopt.egg-info/dependency_links.txt
emopt.egg-info/not-zip-safe
emopt.egg-info/top_level.txt
emopt/data/silicon.csv