Metadata-Version: 1.0
Name: emopt
Version: 0.2.3.1
Summary: A suite of tools for optimizing the shape and topology of electromagnetic structures.
Home-page: https://github.com/anstmichaels/emopt
Author: Andrew Michaels
Author-email: amichaels@berkeley.edu
License: Apache 2.0
Platform: UNKNOWN
